{
    "id": "af-power-elixir-001",
    "content_type": "product",
    "lang": "pl",
    "title": "AF Power Elixir – zaawansowany suplement do pomp dozujących",
    "query_text": "AF Power Elixir suplement pompa dozująca wybarwienie zooksantelle aminokwasy biotyna alanina glutamina leucyna lizyna seryna witaminy fotosynteza wzrost koralowce 4ml 100L 200ml 1000ml 2000ml nie rozcieńczać wstrząsanie lodówka polipowanie kondycja",
    "full_content": "AF Power Elixir to zaawansowany suplement idealny do pomp dozujących, wspomaga wybarwienie zooksantelli koralowców poprzez stały dostęp do najwyższej jakości składników odżywczych. FORMUŁA: Kompleksowa formuła stworzona dla najbardziej wymagających koralowców, opracowana na bazie wieloletnich doświadczeń, gwarantuje idealną równowagę pomiędzy aminokwasami a wartościowymi witaminami. SKŁAD: Zawiera biotynę, alaninę, glutaminę, leucynę, lizynę i serynę, wzbogacony o zestaw specjalnie dobranych witamin, nie zawiera szkodliwych substancji. KORZYŚCI: Zauważalnie przyspiesza wzrost koralowców, podnosi jakość procesu fotosyntezy, zapewnia intensywne wybarwienie koralowców, gwarantuje świetną kondycję poprzez ciągły dostęp do składników odżywczych, wspiera fotosyntezę i naturalne wzorce wzrostu, intensywniejsze wybarwienie przy mocniejszym polipowaniu. SPECYFIKACJA: Dostępny w pojemnościach 200ml, 1000ml, 2000ml, dedykowany do pomp dozujących, nie wymaga rozcieńczania, wstrząsania ani przechowywania w lodówce. DAWKOWANIE: 4ml na 100L wody przy średniej obsadzie koralowców, nie wymaga wcześniejszego przygotowania, po otwarciu przechowywać w temperaturze pokojowej do 30 dni, rozpocząć od połowy dawki i obserwować reakcję koralowców. ZNACZENIE: Aminokwasy są materiałem budulcowym białek niezbędnym do budowania tkanek przez koralowce, regularne dozowanie gwarantuje utrzymanie koralowców w świetnej kondycji.",
    "domain": "seawater",
    "category": "supplements",
    "intent": ["coral_care", "nutrition", "color_enhancement", "growth"],
    "difficulty": "intermediate",
    "url": "https://aquaforest.eu/pl/produkty/seawater/pokarmy-i-suplementacja/af-power-elixir/",
    "tags": ["suplement", "pompa_dozująca", "aminokwasy", "zooksantelle", "wybarwienie", "fotosynteza", "4ml", "200ml", "1000ml", "2000ml", "wzrost"],
    "related_items": ["af-amino-mix", "af-vitality", "af-energy", "af-build"],
    "updated_at": "2025-05-28"
}

